{
  "users": [
    { "id": 1, "name": "Kevin" },
    { "id": 2, "name": "Corey" },
    { "id": 3, "name": "Gentry" },
    { "id": 4, "name": "Alex" },
    { "id": 5, "name": "Nathan" },
    { "id": 6, "name": "Keith" },
    { "id": 7, "name": "Ben" },
    { "id": 8, "name": "Trey" },
    { "id": 9, "name": "Martin" },
    { "id": 10, "name": "Erica" },
    { "id": 11, "name": "Doug" }
  ],
  "todos": [
    { "id": 1, "done": false, "task": "a" },
    { "id": 2, "done": false, "task": "b" },
    { "id": 3, "done": false, "task": "a" },
    { "id": 4, "done": false, "task": "y" },
    { "id": 5, "done": false, "task": "a" },
    { "id": 6, "done": false, "task": "a" },
    { "id": 7, "done": false, "task": "y" },
    { "id": 8, "done": false, "task": "a" },
    { "id": 9, "done": false, "task": "a" }
  ]
}
